{"points":[
    {"lat":50.249596,"lng":18.566320},
    {"lat":50.249912,"lng":18.566585},
    {"lat":50.250214,"lng":18.566835},
    {"lat":50.250564,"lng":18.567073},
    {"lat":50.250738,"lng":18.567341},
    {"lat":50.250683,"lng":18.567989},
    {"lat":50.250632,"lng":18.568616},
    {"lat":50.250701,"lng":18.569203},
    {"lat":50.251173,"lng":18.569625},
    {"lat":50.251557,"lng":18.569965},
    {"lat":50.251876,"lng":18.570234}
    ],
    "time":600,
    "distance":200,
    "name":"Home route",
    "date":1511291963,
    "times":[
        20, 
        15, 
        30, 
        62, 
        20, 
        11, 
        68, 
        123, 
        82, 
        24, 
        46
    ]
}